sc_var/.DS_Store
sc_var/__init__.py
sc_var/method.py
sc_var-1.3.0.dist-info/LICENSE
sc_var-1.3.0.dist-info/METADATA
sc_var-1.3.0.dist-info/WHEEL
sc_var-1.3.0.dist-info/RECORD
